pacu/__init__.py
pacu/__main__.py
pacu/core/__init__.py
pacu/core/base.py
pacu/core/enumerate_iam/__init__.py
pacu/core/enumerate_iam/bruteforce_tests.py
pacu/core/enumerate_iam/generate_bruteforce_tests.py
pacu/core/enumerate_iam/main.py
pacu/core/enumerate_iam/utils/__init__.py
pacu/core/enumerate_iam/utils/json_utils.py
pacu/core/enumerate_iam/utils/remove_metadata.py
pacu/core/lib.py
pacu/core/mixins.py
pacu/core/models.py
pacu/core/secretfinder/regexs.json
pacu/core/secretfinder/utils.py
pacu/main.py
pacu/modules/__init__.py
pacu/modules/acm__enum/__init__.py
pacu/modules/acm__enum/main.py
pacu/modules/api_gateway__create_api_keys/__init__.py
pacu/modules/api_gateway__create_api_keys/main.py
pacu/modules/apigateway__enum/__init__.py
pacu/modules/apigateway__enum/main.py
pacu/modules/aws__enum_account/__init__.py
pacu/modules/aws__enum_account/main.py
pacu/modules/aws__enum_spend/__init__.py
pacu/modules/aws__enum_spend/main.py
pacu/modules/cfn__resource_injection/__init__.py
pacu/modules/cfn__resource_injection/cfn__resource_injection_lambda/.chalice/config.json
pacu/modules/cfn__resource_injection/cfn__resource_injection_lambda/.gitignore
pacu/modules/cfn__resource_injection/cfn__resource_injection_lambda/app.py
pacu/modules/cfn__resource_injection/cfn__resource_injection_lambda/requirements.txt
pacu/modules/cfn__resource_injection/cfn__resource_injection_lambda/tests/conftest.py
pacu/modules/cfn__resource_injection/cfn__resource_injection_lambda/tests/test_app.py
pacu/modules/cfn__resource_injection/main.py
pacu/modules/cfn__resource_injection/tests/test_cfn__resource_injection.py
pacu/modules/cloudformation__download_data/__init__.py
pacu/modules/cloudformation__download_data/main.py
pacu/modules/cloudtrail__csv_injection/__init__.py
pacu/modules/cloudtrail__csv_injection/main.py
pacu/modules/cloudtrail__download_event_history/__init__.py
pacu/modules/cloudtrail__download_event_history/main.py
pacu/modules/cloudwatch__download_logs/__init__.py
pacu-1.6.1.dist-info/LICENSE
pacu-1.6.1.dist-info/METADATA
pacu-1.6.1.dist-info/WHEEL
pacu-1.6.1.dist-info/entry_points.txt
pacu-1.6.1.dist-info/RECORD
